{
  "cluster_information": {
    "cluster_id": "0x0400",
    "name": "Illuminance Measurement",
    "description": "This cluster provides an interface to illuminance measurement functionality, including configuration and provision of notifications."
  },
  "derived_datatypes": [],
  "commands": [],
  "attributes": [
    {
      "id": "0x0000",
      "name": "MeasuredValue",
      "data_type": "uint16",
      "value_range": {
        "min": "0",
        "max": "65535"
      },
      "description": "MeasuredValue attribute",
      "privilege": "V",
      "writable": false,
      "access": "R"
    },
    {
      "id": "0x0001",
      "name": "MinMeasuredValue",
      "data_type": "uint16",
      "value_range": {
        "min": "0",
        "max": "65535"
      },
      "description": "MinMeasuredValue attribute",
      "privilege": "V",
      "writable": false,
      "access": "R"
    },
    {
      "id": "0x0002",
      "name": "MaxMeasuredValue",
      "data_type": "uint16",
      "value_range": {
        "min": "0",
        "max": "65535"
      },
      "description": "MaxMeasuredValue attribute",
      "privilege": "V",
      "writable": false,
      "access": "R"
    },
    {
      "id": "0x0003",
      "name": "Tolerance",
      "data_type": "uint16",
      "value_range": {
        "min": "0",
        "max": "65535"
      },
      "description": "Tolerance attribute",
      "privilege": "V",
      "writable": false,
      "access": "R"
    },
    {
      "id": "0x0004",
      "name": "LightSensorType",
      "data_type": "enum8",
      "value_range": {},
      "description": "LightSensorType attribute",
      "privilege": "V",
      "writable": false,
      "access": "R"
    }
  ],
  "events": []
}