{
  "cluster_information": {
    "cluster_id": "0x0004",
    "name": "Groups",
    "description": "SHALL support the FeatureMap global attribute:\n\nBit          Code         Name         Def          Description\n\n0            GN           Group        0            The ability to store a name for a group."
  },
  "derived_datatypes": [],
  "commands": [
    {
      "id": "0x00",
      "name": "AddGroup",
      "parameters": [],
      "privilege": "O",
      "side": "client"
    },
    {
      "id": "0x01",
      "name": "ViewGroup",
      "parameters": [],
      "privilege": "O",
      "side": "client"
    },
    {
      "id": "0x02",
      "name": "GetGroupMember",
      "parameters": [],
      "privilege": "O",
      "side": "client"
    },
    {
      "id": "0x03",
      "name": "RemoveGroup",
      "parameters": [],
      "privilege": "O",
      "side": "client"
    },
    {
      "id": "0x04",
      "name": "RemoveAllGroups",
      "parameters": [],
      "privilege": "O",
      "side": "client"
    },
    {
      "id": "0x05",
      "name": "AddGroupIfIdenti",
      "parameters": [],
      "privilege": "O",
      "side": "client"
    },
    {
      "id": "0x00",
      "name": "AddGroupRe",
      "parameters": [],
      "privilege": "O",
      "side": "client"
    },
    {
      "id": "0x01",
      "name": "ViewGroupRe",
      "parameters": [],
      "privilege": "O",
      "side": "client"
    },
    {
      "id": "0x02",
      "name": "GetGroupMember",
      "parameters": [],
      "privilege": "O",
      "side": "client"
    },
    {
      "id": "0x03",
      "name": "RemoveGroupRe",
      "parameters": [],
      "privilege": "O",
      "side": "client"
    }
  ],
  "attributes": [
    {
      "id": "0x0000",
      "name": "NameSupport",
      "data_type": "unknown",
      "value_range": {},
      "description": "",
      "privilege": "V",
      "writable": false
    }
  ],
  "events": []
}