{
  "cluster_information": {
    "cluster_id": "0x050e",
    "name": "Account Login",
    "description": "SHALL support the FeatureMap bitmap attribute as defined below."
  },
  "derived_datatypes": [],
  "commands": [
    {
      "id": "0x00",
      "name": "GetSetupPIN",
      "parameters": [],
      "privilege": "O",
      "side": "client"
    },
    {
      "id": "0x01",
      "name": "GetSetupPIN",
      "parameters": [],
      "privilege": "O",
      "side": "client"
    },
    {
      "id": "0x02",
      "name": "Login",
      "parameters": [],
      "privilege": "O",
      "side": "client"
    },
    {
      "id": "0x03",
      "name": "Logout",
      "parameters": [],
      "privilege": "O",
      "side": "client"
    }
  ],
  "attributes": [],
  "events": []
}